{
  "hash": "b5977402",
  "configHash": "70bfbc46",
  "lockfileHash": "9f3ab9a9",
  "browserHash": "fe69f676",
  "optimized": {
    "react": {
      "src": "../../node_modules/react/index.js",
      "file": "react.js",
      "fileHash": "ea79f85b",
      "needsInterop": true
    },
    "react-dom": {
      "src": "../../node_modules/react-dom/index.js",
      "file": "react-dom.js",
      "fileHash": "e59ae6a1",
      "needsInterop": true
    },
    "react/jsx-dev-runtime": {
      "src": "../../node_modules/react/jsx-dev-runtime.js",
      "file": "react_jsx-dev-runtime.js",
      "fileHash": "0beae637",
      "needsInterop": true
    },
    "react/jsx-runtime": {
      "src": "../../node_modules/react/jsx-runtime.js",
      "file": "react_jsx-runtime.js",
      "fileHash": "30ccd414",
      "needsInterop": true
    },
    "@gravity-ui/icons": {
      "src": "../../node_modules/@gravity-ui/icons/esm/index.js",
      "file": "@gravity-ui_icons.js",
      "fileHash": "be259f40",
      "needsInterop": false
    },
    "@gravity-ui/uikit": {
      "src": "../../node_modules/@gravity-ui/uikit/build/esm/index.js",
      "file": "@gravity-ui_uikit.js",
      "fileHash": "5e62559c",
      "needsInterop": false
    },
    "@tanstack/react-query": {
      "src": "../../node_modules/@tanstack/react-query/build/modern/index.js",
      "file": "@tanstack_react-query.js",
      "fileHash": "e666aa0a",
      "needsInterop": false
    },
    "@tanstack/react-router": {
      "src": "../../node_modules/@tanstack/react-router/dist/esm/index.js",
      "file": "@tanstack_react-router.js",
      "fileHash": "1ea4354d",
      "needsInterop": false
    },
    "@tanstack/router-devtools": {
      "src": "../../node_modules/@tanstack/router-devtools/dist/esm/index.js",
      "file": "@tanstack_router-devtools.js",
      "fileHash": "e8abd621",
      "needsInterop": false
    },
    "clsx": {
      "src": "../../node_modules/clsx/dist/clsx.mjs",
      "file": "clsx.js",
      "fileHash": "f4e5d0c6",
      "needsInterop": false
    },
    "lucide-react": {
      "src": "../../node_modules/lucide-react/dist/esm/lucide-react.js",
      "file": "lucide-react.js",
      "fileHash": "c87d96d3",
      "needsInterop": false
    },
    "query-string": {
      "src": "../../node_modules/query-string/index.js",
      "file": "query-string.js",
      "fileHash": "21e7a6d5",
      "needsInterop": false
    },
    "react-dom/client": {
      "src": "../../node_modules/react-dom/client.js",
      "file": "react-dom_client.js",
      "fileHash": "77e79bec",
      "needsInterop": true
    }
  },
  "chunks": {
    "BaseTanStackRouterDevtoolsPanel-WQSUH5CP": {
      "file": "BaseTanStackRouterDevtoolsPanel-WQSUH5CP.js"
    },
    "FloatingTanStackRouterDevtools-A367S7O4": {
      "file": "FloatingTanStackRouterDevtools-A367S7O4.js"
    },
    "chunk-LWAAGITP": {
      "file": "chunk-LWAAGITP.js"
    },
    "chunk-KDVGFZWC": {
      "file": "chunk-KDVGFZWC.js"
    },
    "chunk-TGF67CJS": {
      "file": "chunk-TGF67CJS.js"
    },
    "chunk-VHHZD562": {
      "file": "chunk-VHHZD562.js"
    },
    "chunk-KV4S5HPH": {
      "file": "chunk-KV4S5HPH.js"
    },
    "chunk-T46KWSWP": {
      "file": "chunk-T46KWSWP.js"
    },
    "chunk-XC26ZK3T": {
      "file": "chunk-XC26ZK3T.js"
    },
    "chunk-E55NSNTN": {
      "file": "chunk-E55NSNTN.js"
    },
    "chunk-4MBMRILA": {
      "file": "chunk-4MBMRILA.js"
    }
  }
}